moat/src/__init__.py
moat/src/_cfg.yaml
moat/src/_main.py
moat/src/_repo.py
moat/src/_toml.py
moat/src/_util.py
moat/src/build.py
moat/src/dep-update.py
moat/src/inspect.py
moat/src/move.py
moat/src/test.py
moat/src/_templates/moat/__init__.py
moat/src/_templates/moat/_main.py
moat/src/_templates/packaging/pyproject.default.yaml
moat/src/_templates/packaging/pyproject.forced.yaml
moat/src/api/__init__.py
moat/src/api/_common.py
moat/src/api/forgejo.py
moat/src/api/github.py
moat/src/api/localgit.py
moat/src/api/radicle.py
moat_src-0.10.6.dist-info/licenses/LICENSE.txt
moat_src-0.10.6.dist-info/METADATA
moat_src-0.10.6.dist-info/WHEEL
moat_src-0.10.6.dist-info/top_level.txt
moat_src-0.10.6.dist-info/RECORD
