Metadata-Version: 2.4
Name: moat-src
Version: 0.10.6
Summary: Tools for managing the MoaT sources
Author-email: Matthias Urlichs <matthias@urlichs.de>
Project-URL: homepage, https://m-o-a-t.org
Project-URL: repository, https://github.com/M-o-a-T/moat
Keywords: MoaT
Classifier: Intended Audience :: Developers
Classifier: Programming Language :: Python :: 3
Classifier: Framework :: AsyncIO
Classifier: Framework :: Trio
Classifier: Framework :: AnyIO
Classifier: Development Status :: 4 - Beta
Requires-Python: >=3.8
License-File: LICENSE.txt
Requires-Dist: anyio~=4.2
Requires-Dist: tomlkit~=0.12
Requires-Dist: asyncclick
Requires-Dist: gitpython
Requires-Dist: packaging
Requires-Dist: moat-lib-config~=0.1.1
Requires-Dist: moat-lib-run~=0.1.1
Requires-Dist: moat-util~=0.62.2
Dynamic: license-file
